dimutex/__init__.py
dimutex/_exceptions.py
dimutex/_gcs.py
dimutex-1.3.1.dist-info/LICENSE
dimutex-1.3.1.dist-info/WHEEL
dimutex-1.3.1.dist-info/METADATA
dimutex-1.3.1.dist-info/RECORD
