Metadata-Version: 2.1
Name: dimutex
Version: 1.3.1
Summary: Mutex implementation for distributed systems.
Keywords: mutex,google,google cloud,gcs,gcp,microservices
Author-email: Gram <gram@orsinium.dev>
Requires-Python: >=3.6
Classifier: Development Status :: 5 - Production/Stable
Classifier: Intended Audience :: Developers
Classifier: License :: OSI Approved :: MIT License
Classifier: Programming Language :: Python
Classifier: Topic :: Software Development
Requires-Dist: aiohttp
Requires-Dist: gcloud-aio-auth
Requires-Dist: bandit ; extra == "lint"
Requires-Dist: flake8 ; extra == "lint"
Requires-Dist: isort ; extra == "lint"
Requires-Dist: mypy ; extra == "lint"
Requires-Dist: unify ; extra == "lint"
Requires-Dist: pytest>=6.2.0 ; extra == "test"
Requires-Dist: pytest-asyncio ; extra == "test"
Requires-Dist: pytest-cov ; extra == "test"
Project-URL: Source, https://github.com/orsinium-labs/dimutex
Provides-Extra: lint
Provides-Extra: test
